freenlpc/__init__.py
freenlpc/freenlpc.py
freenlpc/nlpcloudd.py
freenlpc-0.2.3.dist-info/LICENSE
freenlpc-0.2.3.dist-info/METADATA
freenlpc-0.2.3.dist-info/WHEEL
freenlpc-0.2.3.dist-info/top_level.txt
freenlpc-0.2.3.dist-info/RECORD
