Metadata-Version: 2.1
Name: freenlpc
Version: 0.2.3
Summary: A wrapper for nlpcloud free-tier services with no requests per minute limits.
Author: Abdelrhman Nile
Author-email: <abdelrhmannile@gmail.com>
Keywords: python,natural languge processing,nlp,deep learning,AI,GPT,LLMS,nlpcloud
Classifier: Development Status :: 1 - Planning
Classifier: Intended Audience :: Developers
Classifier: Programming Language :: Python :: 3
Classifier: Operating System :: Unix
Classifier: Operating System :: MacOS :: MacOS X
Classifier: Operating System :: Microsoft :: Windows
License-File: LICENSE
Requires-Dist: requests
